codecalculatorapp/__init__.py
codecalculatorapp-0.1.dist-info/LICENCE.txt
codecalculatorapp-0.1.dist-info/METADATA
codecalculatorapp-0.1.dist-info/WHEEL
codecalculatorapp-0.1.dist-info/top_level.txt
codecalculatorapp-0.1.dist-info/RECORD
