Metadata-Version: 2.1
Name: codecalculatorapp
Version: 0.1
Summary: Basic calculator functions
Home-page: UNKNOWN
Author: Roseanne Abunie
Author-email: rose.abunie@gmail.com
License: UNKNOWN
Platform: UNKNOWN
Classifier: Programming Language :: Python :: 3
Classifier: License :: OSI Approved :: MIT License
Classifier: Operating System :: OS Independent
License-File: LICENCE.txt
